global_service/__init__.py
global_service/global_service.py
global_service_django-0.1.7.dist-info/METADATA
global_service_django-0.1.7.dist-info/WHEEL
global_service_django-0.1.7.dist-info/top_level.txt
global_service_django-0.1.7.dist-info/RECORD
