Metadata-Version: 2.4
Name: global_service_django
Version: 0.1.7
Summary: A global logging and service utilities package for Python projects, designed for seamless integration with Django applications. Developed by Lighthouse Info System Pvt Ltd., this package provides robust logging, configuration, and service management tools to enhance reliability and maintainability in Django-based projects.
Home-page: https://github.com/NAT-TEAM-LIGHTHOUSE/Python-Projects/tree/python_global_django_pkg
Author: Rohit Jagatp
Author-email: rohit.jagatp@lighthouseindia.com
License: MIT
Classifier: Programming Language :: Python :: 3
Classifier: License :: OSI Approved :: MIT License
Classifier: Operating System :: OS Independent
Requires-Python: >=3.9
Requires-Dist: requests
Requires-Dist: python-dotenv
Requires-Dist: cx_Oracle
Dynamic: author
Dynamic: author-email
Dynamic: classifier
Dynamic: description
Dynamic: description-content-type
Dynamic: home-page
Dynamic: license
Dynamic: requires-dist
Dynamic: requires-python
Dynamic: summary
